setup.cfg
setup.py
commanderiot/__init__.py
commanderiot/commanderAPIClient.py
commanderiot/commanderToken.py
commanderiot/version.py
commanderiot.egg-info/PKG-INFO
commanderiot.egg-info/SOURCES.txt
commanderiot.egg-info/dependency_links.txt
commanderiot.egg-info/requires.txt
commanderiot.egg-info/top_level.txt
commanderiot/helpers/__init__.py
commanderiot/helpers/commanderHTTPClient.py
commanderiot/objects/__init__.py
commanderiot/objects/alarms.py
commanderiot/objects/devices.py
commanderiot/objects/networks.py
commanderiot/objects/points.py
commanderiot/objects/projects.py
commanderiot/objects/schedules.py
commanderiot/objects/trends.py