Metadata-Version: 1.1
Name: commanderiot
Version: 0.3
Summary: Python client for Commander Web API
Home-page: https://github.com/HawkenIndustries/pycommander/
Author: Gebin Maxey
Author-email: support@hawkenio.com
License: MIT
Download-URL: https://github.com/HawkenIndustries/pycommander/archive/0.3.tar.gz
Keywords: IOT,API,Embedded Systems
Platform: UNKNOWN
Classifier: Development Status :: 3 - Alpha
Classifier: Intended Audience :: Developers
Classifier: Topic :: Software Development :: Build Tools
Classifier: License :: OSI Approved :: MIT License
Classifier: Programming Language :: Python :: 3
Classifier: Programming Language :: Python :: 3.4
Classifier: Programming Language :: Python :: 3.5
Classifier: Programming Language :: Python :: 3.6
Classifier: Programming Language :: Python :: 3.7
Classifier: Programming Language :: Python :: 3.8
